arg_robotics_tools/__init__.py
arg_robotics_tools/_modidx.py
arg_robotics_tools/_nbdev.py
arg_robotics_tools/anchor_logging.py
arg_robotics_tools/camera_projection.py
arg_robotics_tools/get_ip.py
arg_robotics_tools/mqtt.py
arg_robotics_tools/random_map.py
arg_robotics_tools/robot_model.py
arg_robotics_tools/tsp.py
arg_robotics_tools/utils.py
arg_robotics_tools/uwb.py
arg_robotics_tools/video2picture.py
arg_robotics_tools/websocket_rosbridge.py
arg_robotics_tools/xbee_coding.py
arg_robotics_tools-0.0.16.dist-info/LICENSE
arg_robotics_tools-0.0.16.dist-info/METADATA
arg_robotics_tools-0.0.16.dist-info/WHEEL
arg_robotics_tools-0.0.16.dist-info/top_level.txt
arg_robotics_tools-0.0.16.dist-info/RECORD
